{
  "logoMenu":["开始游戏","继续游戏","退出游戏"],
  "currencyMenu":["是","否","返回"],
  "sexMenu":["男","女","扶她","无性","随机","返回"],
  "inputNickName":["是","否","与姓名相同","返回"],
  "inputSelfName":["是","否","返回"],
  "detailedSetting1":["{SelfName}如今已是垂垂老矣，安于天命了","依稀记得曾经青春年少时","{SelfName}已经成年了呢","年轻就是{SelfName}最大的本钱呢！","嘎唔嘎唔！"],
  "detailedSetting2":["可爱的猫咪","吸血的蝙蝠","迷人的狐狸","勇猛的狮子","并不喜欢小动物"],
  "detailedSetting3":["{SelfName}早已是经验丰富，身经百战了",
    "大概只是普通的程度吧？不多也不少的样子","只有极少的性经验哦，说是纯情也不为过","性经验什么的完全没有过，你在问什么呢！变态！"],
  "detailedSetting4":["这种时候当然是需要挺身而出了","还是赶紧报警好了","万一被连累怎么办，赶紧跑吧"],
  "detailedSetting5":["太好了，马上就到！","如果没什么事情的话可能会去","不行，绝对不行，说不定是传销什么的，绝对不能去"],
  "detailedSetting6":["这世上还没有问题能难得了{SelfName}","只要努力前进的话，一定能克服一切困难","不行，还是放弃吧，{SelfName}这种人也就如此而已罢了"],
  "detailedSetting7":["自然是义不容辞，尽己所能的去帮助了","看情况而定吧，不会随意帮助别人","不行不行，我帮他以后，他赖上我怎么办"],
  "detailedSetting8":["略显瘦弱，不太结实的样子","一般般吧，不胖也不瘦","稍微有些超重了","大概算是比较胖的类型","毫无疑问是个胖子","已经胖到极限了"],
  "acknowledgmentAttribute":["这样就可以了","请给{SelfName}一个重头再来的机会"],
  "cmdSwitch":["-","+"],
  "mainMenu":["起床","查看属性","更换服装","迷之商店"],
  "systemMenu":["系统设置","查看帮助","储存游戏","读取存档"],
  "seeAttrPanelHandle":["查看装备和道具","查看经验和能力","查看素质和刻印"],
  "changeSavePage":["上一页","返回","下一页"],
  "overlaySave":["覆盖","删除","返回"],
  "confirmationOverlaySave":["确定","再考虑下"],
  "loadSaveAsk":["读取","删除","返回"],
  "confirmationLoadSave":["确定","再选选"],
  "confirmationRemoveSave":["确定","还是算了"],
  "seeAttrOnEveryTime":["上一个人","返回","下一个人"],
  "seePlayerList":["上一页","返回","下一页"],
  "inSceneList1":["移动","查看属性","查看{NickName}的属性"],
  "seeMap":["返回场景"]
}